{"type": "Feature", "id": 12514718, "properties": {"woe:id": 12514718, "woe:parent_id": 480441, "woe:name": "Kagul Southeast Airport", "woe:placetype": 14, "woe:placetype_name": "Airport", "woe:lang": "ENG", "iso:country": "MD", "meta:provider": ["geoplanet:7.3.1", "geoplanet:7.3.2", "geoplanet:7.4.0", "geoplanet:7.4.1", "geoplanet:7.5.1", "geoplanet:7.5.2", "geoplanet:7.6.0", "geoplanet:7.8.1", "geoplanet:7.9.0", "geoplanet:7.10.0", "geoplanet:8.0.0", "woeplanet:8.0.0"], "meta:indexed": "2020-08-20T20:57:52.236348", "meta:updated": "2020-08-22T02:50:43.837808", "woe:hierarchy": {"continent": 24865675, "country": 23424885, "town": 0, "planet": 1, "county": 0, "suburb": 0, "state": 20069882, "region": 0, "localadmin": 0}, "woe:timezone_id": 28350894, "woe:hash": "u8hhg1ftgp62", "woe:centroid": [28.260401, 45.8456], "geom:latitude": 45.8456, "geom:longitude": 28.260401, "geom:hash": "u8hhg1ftgp62", "woe:latitude": 45.8456, "geom:centroid": [28.260401, 45.8456], "woe:longitude": 28.260401, "woe:repo": "woeplanet-airport-md"}, "geometry": {"coordinates": [28.260401, 45.8456], "type": "Point"}}