{"type": "Feature", "id": 12514715, "properties": {"woe:id": 12514715, "woe:parent_id": 480639, "woe:name": "Beltsy Northeast Airport", "woe:placetype": 14, "woe:placetype_name": "Airport", "woe:lang": "ENG", "iso:country": "MD", "meta:provider": ["geoplanet:7.3.1", "geoplanet:7.3.2", "geoplanet:7.4.0", "geoplanet:7.4.1", "geoplanet:7.5.1", "geoplanet:7.5.2", "geoplanet:7.6.0", "geoplanet:7.8.1", "geoplanet:7.9.0", "geoplanet:7.10.0", "geoplanet:8.0.0", "woeplanet:8.0.0"], "meta:indexed": "2020-08-20T20:57:52.233653", "meta:updated": "2020-08-22T02:50:43.836422", "woe:hierarchy": {"continent": 24865675, "country": 23424885, "town": 0, "planet": 1, "county": 0, "suburb": 0, "state": 55948197, "region": 0, "localadmin": 0}, "woe:timezone_id": 28350894, "woe:hash": "u8eb07yykv9c", "woe:centroid": [27.7939, 47.834202], "geom:latitude": 47.834202, "geom:longitude": 27.7939, "geom:hash": "u8eb07yykv9c", "woe:latitude": 47.834202, "geom:centroid": [27.7939, 47.834202], "woe:longitude": 27.7939, "woe:repo": "woeplanet-airport-md"}, "geometry": {"coordinates": [27.7939, 47.834202], "type": "Point"}}